{
  "010524": {
    "date": "2026-06-23",
    "est": -3.5607
  },
  "017560": {
    "date": "2026-06-22",
    "est": 2.2332
  },
  "015395": {
    "date": "2026-06-23",
    "est": -4.2102
  },
  "015968": {
    "date": "2026-06-23",
    "est": -2.8543
  },
  "004433": {
    "date": "2026-06-23",
    "est": -8.1186
  },
  "017992": {
    "date": "2026-06-18",
    "est": -3.7835
  },
  "017193": {
    "date": "2026-06-18",
    "est": -1.183
  },
  "019165": {
    "date": "2026-06-23",
    "est": -8.3997
  },
  "016708": {
    "date": "2026-06-23",
    "est": -7.9972
  },
  "022321": {
    "date": "2026-06-23",
    "est": -7.3155
  },
  "011631": {
    "date": "2026-06-23",
    "est": -7.8532
  },
  "022084": {
    "date": "2026-06-23",
    "est": -5.7204
  },
  "017811": {
    "date": "2026-06-23",
    "est": -0.0164
  },
  "018133": {
    "date": "2026-06-23",
    "est": -7.8115
  },
  "015596": {
    "date": "2026-06-23",
    "est": -7.8913
  },
  "025651": {
    "date": "2026-06-23",
    "est": -3.6262
  },
  "018168": {
    "date": "2026-06-23",
    "est": -8.3489
  },
  "023037": {
    "date": "2026-06-23",
    "est": -6.7273
  },
  "013081": {
    "date": "2026-06-23",
    "est": -7.9167
  },
  "017470": {
    "date": "2026-06-18",
    "est": 4.9925
  },
  "011068": {
    "date": "2026-06-23",
    "est": -7.3191
  },
  "020124": {
    "date": "2026-06-18",
    "est": -2.8196
  },
  "014855": {
    "date": "2026-06-23",
    "est": 0.04
  },
  "012970": {
    "date": "2026-06-18",
    "est": 5.7949
  },
  "014143": {
    "date": "2026-06-23",
    "est": -2.1277
  },
  "021533": {
    "date": "2026-06-18",
    "est": 1.8889
  },
  "012630": {
    "date": "2026-06-23",
    "est": -2.5831
  },
  "024424": {
    "date": "2026-06-23",
    "est": -0.0333
  },
  "020640": {
    "date": "2026-06-23",
    "est": -0.2106
  },
  "019571": {
    "date": "2026-06-23",
    "est": -0.487
  },
  "018777": {
    "date": "2026-06-23",
    "est": -1.7299
  },
  "020357": {
    "date": "2026-06-23",
    "est": -0.2334
  },
  "019633": {
    "date": "2026-06-23",
    "est": -0.4581
  },
  "021894": {
    "date": "2026-06-23",
    "est": -0.2974
  },
  "023829": {
    "date": "2026-06-18",
    "est": 1.9699
  },
  "020465": {
    "date": "2026-06-23",
    "est": -0.1479
  },
  "021492": {
    "date": "2026-06-23",
    "est": -0.0012
  },
  "007491": {
    "date": "2026-06-23",
    "est": 0.2822
  },
  "014194": {
    "date": "2026-06-18",
    "est": 5.1529
  },
  "024975": {
    "date": "2026-06-18",
    "est": 1.3083
  },
  "002692": {
    "date": "2026-06-18",
    "est": 2.4882
  },
  "021719": {
    "date": "2026-06-18",
    "est": 3.8011
  },
  "020629": {
    "date": "2026-06-23",
    "est": -2.3458
  },
  "023652": {
    "date": "2026-06-18",
    "est": 6.4033
  },
  "025209": {
    "date": "2026-06-23",
    "est": -1.0638
  },
  "016874": {
    "date": "2026-06-18",
    "est": 2.1062
  },
  "005967": {
    "date": "2026-06-18",
    "est": 3.917
  },
  "017745": {
    "date": "2026-06-18",
    "est": 5.4683
  },
  "010623": {
    "date": "2026-06-18",
    "est": 3.0472
  },
  "025500": {
    "date": "2026-06-23",
    "est": -1.696
  },
  "021608": {
    "date": "2026-06-23",
    "est": -2.3542
  },
  "024418": {
    "date": "2026-06-23",
    "est": -0.7697
  },
  "008888": {
    "date": "2026-06-23",
    "est": -1.9332
  },
  "018816": {
    "date": "2026-06-23",
    "est": -1.292
  },
  "160324": {
    "date": "2026-06-18",
    "est": 2.6409
  },
  "014320": {
    "date": "2026-06-18",
    "est": 4.7822
  },
  "022351": {
    "date": "2026-06-18",
    "est": 6.821
  },
  "002910": {
    "date": "2026-06-23",
    "est": -0.3876
  },
  "019114": {
    "date": "2026-06-23",
    "est": -0.0994
  },
  "007046": {
    "date": "2026-06-23",
    "est": -3.1013
  },
  "015790": {
    "date": "2026-06-23",
    "est": -2.935
  },
  "018363": {
    "date": "2026-06-18",
    "est": 1.4076
  },
  "010052": {
    "date": "2026-06-23",
    "est": -2.4746
  },
  "009751": {
    "date": "2026-06-23",
    "est": -2.8304
  },
  "004321": {
    "date": "2026-06-23",
    "est": -4.2878
  },
  "025491": {
    "date": "2026-06-18",
    "est": 0.747
  },
  "000690": {
    "date": "2026-06-18",
    "est": 1.923
  },
  "002067": {
    "date": "2026-06-18",
    "est": 1.8182
  },
  "015839": {
    "date": "2026-06-23",
    "est": -2.8703
  },
  "025647": {
    "date": "2026-06-23",
    "est": -4.2384
  },
  "019144": {
    "date": "2026-06-23",
    "est": -4.3757
  },
  "025733": {
    "date": "2026-06-18",
    "est": -1.7185
  },
  "024195": {
    "date": "2026-06-18",
    "est": 1.4179
  },
  "025693": {
    "date": "2026-06-18",
    "est": 0.3593
  },
  "023531": {
    "date": "2026-06-18",
    "est": 0.5026
  },
  "024689": {
    "date": "2026-06-18",
    "est": 0.4921
  },
  "009854": {
    "date": "2026-06-23",
    "est": -3.6559
  },
  "024913": {
    "date": "2026-06-18",
    "est": 0.5029
  },
  "024349": {
    "date": "2026-06-18",
    "est": 0.473
  },
  "025949": {
    "date": "2026-06-18",
    "est": 1.2215
  },
  "025422": {
    "date": "2026-06-23",
    "est": -3.2481
  },
  "001438": {
    "date": "2026-06-23",
    "est": -1.3443
  },
  "004320": {
    "date": "2026-06-23",
    "est": -2.5092
  },
  "017462": {
    "date": "2026-06-23",
    "est": -3.6462
  },
  "018291": {
    "date": "2026-06-23",
    "est": -0.6463
  },
  "011892": {
    "date": "2026-06-23",
    "est": -3.3979
  },
  "011452": {
    "date": "2026-06-23",
    "est": -4.0278
  },
  "018957": {
    "date": "2026-06-23",
    "est": -2.0021
  },
  "009009": {
    "date": "2026-06-18",
    "est": 2.2307
  },
  "006888": {
    "date": "2026-06-23",
    "est": -2.905
  },
  "010238": {
    "date": "2026-06-23",
    "est": -4.0152
  },
  "013470": {
    "date": "2026-06-23",
    "est": -2.4937
  },
  "011120": {
    "date": "2026-06-23",
    "est": -1.6314
  },
  "011370": {
    "date": "2026-06-23",
    "est": -0.6423
  },
  "005866": {
    "date": "2026-06-23",
    "est": -3.6732
  },
  "017103": {
    "date": "2026-06-23",
    "est": -3.8685
  },
  "519771": {
    "date": "2026-06-18",
    "est": 2.3474
  },
  "017489": {
    "date": "2026-06-23",
    "est": -3.3449
  },
  "009645": {
    "date": "2026-06-23",
    "est": -4.086
  },
  "021528": {
    "date": "2026-06-23",
    "est": -2.8654
  },
  "006503": {
    "date": "2026-06-23",
    "est": -2.5705
  },
  "007114": {
    "date": "2026-06-18",
    "est": 3.7397
  },
  "016371": {
    "date": "2026-06-23",
    "est": -2.5891
  },
  "022365": {
    "date": "2026-06-23",
    "est": -3.9469
  },
  "002112": {
    "date": "2026-06-23",
    "est": -4.5119
  },
  "001407": {
    "date": "2026-06-23",
    "est": -3.2035
  },
  "010034": {
    "date": "2026-06-22",
    "est": -1.3715
  },
  "002170": {
    "date": "2026-06-18",
    "est": 2.0809
  },
  "024473": {
    "date": "2026-06-22",
    "est": 0.3826
  },
  "013722": {
    "date": "2026-06-22",
    "est": 0.3823
  },
  "004753": {
    "date": "2026-06-23",
    "est": -2.5656
  },
  "017736": {
    "date": "2026-06-23",
    "est": -4.1893
  },
  "001150": {
    "date": "2026-06-23",
    "est": -3.7218
  },
  "015667": {
    "date": "2026-06-23",
    "est": -4.0556
  },
  "001630": {
    "date": "2026-06-18",
    "est": 1.6239
  },
  "023754": {
    "date": "2026-06-23",
    "est": -3.0016
  },
  "013346": {
    "date": "2026-06-18",
    "est": 5.2051
  },
  "015642": {
    "date": "2026-06-18",
    "est": 0.251
  },
  "020065": {
    "date": "2026-06-23",
    "est": -3.8439
  },
  "020486": {
    "date": "2026-06-23",
    "est": -3.8031
  },
  "023602": {
    "date": "2026-06-23",
    "est": -2.6016
  },
  "018049": {
    "date": "2026-06-23",
    "est": -1.9464
  },
  "012183": {
    "date": "2026-06-23",
    "est": -3.0709
  },
  "018463": {
    "date": "2026-06-23",
    "est": -4.5276
  },
  "016074": {
    "date": "2026-06-23",
    "est": -2.2903
  },
  "020485": {
    "date": "2026-06-18",
    "est": 0.7894
  },
  "020594": {
    "date": "2026-06-23",
    "est": -2.342
  },
  "012847": {
    "date": "2026-06-23",
    "est": -2.0965
  },
  "018386": {
    "date": "2026-06-18",
    "est": 0.8247
  },
  "019062": {
    "date": "2026-06-23",
    "est": -2.3219
  },
  "012637": {
    "date": "2026-06-18",
    "est": 1.1012
  },
  "021536": {
    "date": "2026-06-18",
    "est": 0.7902
  },
  "021615": {
    "date": "2026-06-18",
    "est": 0.807
  },
  "020266": {
    "date": "2026-06-23",
    "est": -3.2478
  },
  "019116": {
    "date": "2026-06-23",
    "est": -4.2527
  },
  "011705": {
    "date": "2026-06-23",
    "est": -1.1893
  },
  "021964": {
    "date": "2026-06-18",
    "est": -1.0004
  },
  "012620": {
    "date": "2026-06-18",
    "est": 0.8328
  },
  "005538": {
    "date": "2026-06-23",
    "est": -2.6615
  },
  "005600": {
    "date": "2026-06-23",
    "est": -3.1586
  },
  "010032": {
    "date": "2026-06-23",
    "est": -4.1749
  },
  "016020": {
    "date": "2026-06-18",
    "est": -1.3508
  },
  "012863": {
    "date": "2026-06-18",
    "est": -1.4143
  },
  "016567": {
    "date": "2026-06-18",
    "est": -1.3312
  },
  "017223": {
    "date": "2026-06-18",
    "est": -1.3125
  },
  "018927": {
    "date": "2026-06-18",
    "est": -1.3641
  },
  "013180": {
    "date": "2026-06-18",
    "est": -1.003
  },
  "011143": {
    "date": "2026-06-23",
    "est": -5.2132
  },
  "024738": {
    "date": "2026-06-23",
    "est": -2.5974
  },
  "021654": {
    "date": "2026-06-18",
    "est": -0.0004
  },
  "023159": {
    "date": "2026-06-23",
    "est": -3.7644
  },
  "020425": {
    "date": "2026-06-23",
    "est": -2.0448
  },
  "025924": {
    "date": "2026-06-18",
    "est": -2.7138
  },
  "006168": {
    "date": "2026-06-23",
    "est": -2.859
  },
  "008182": {
    "date": "2026-06-23",
    "est": -1.4184
  },
  "023567": {
    "date": "2026-06-23",
    "est": -1.9011
  },
  "017074": {
    "date": "2026-06-23",
    "est": -3.6106
  },
  "017994": {
    "date": "2026-06-23",
    "est": -0.2701
  },
  "005165": {
    "date": "2026-06-23",
    "est": -2.0112
  },
  "007519": {
    "date": "2026-06-23",
    "est": -1.7516
  },
  "021986": {
    "date": "2026-06-18",
    "est": -0.8031
  },
  "017968": {
    "date": "2026-06-23",
    "est": -0.029
  },
  "014409": {
    "date": "2026-06-23",
    "est": -1.8452
  },
  "016531": {
    "date": "2026-06-23",
    "est": -0.7085
  },
  "000796": {
    "date": "2026-06-23",
    "est": -1.3776
  },
  "021490": {
    "date": "2026-06-23",
    "est": -1.1209
  },
  "025942": {
    "date": "2026-06-23",
    "est": -1.3138
  },
  "015829": {
    "date": "2026-06-18",
    "est": 0.741
  },
  "001770": {
    "date": "2026-06-23",
    "est": -1.1779
  },
  "015401": {
    "date": "2026-06-23",
    "est": -2.1621
  },
  "018125": {
    "date": "2026-06-23",
    "est": -1.3737
  },
  "019412": {
    "date": "2026-06-23",
    "est": -2.2668
  },
  "019458": {
    "date": "2026-06-23",
    "est": -1.1659
  },
  "016076": {
    "date": "2026-06-23",
    "est": -1.0465
  },
  "018241": {
    "date": "2026-06-23",
    "est": -1.5976
  },
  "024620": {
    "date": "2026-06-18",
    "est": 2.5638
  },
  "020608": {
    "date": "2026-06-18",
    "est": 2.4672
  },
  "018095": {
    "date": "2026-06-18",
    "est": 2.4364
  },
  "021302": {
    "date": "2026-06-18",
    "est": 2.4079
  },
  "020482": {
    "date": "2026-06-18",
    "est": 2.4688
  },
  "020256": {
    "date": "2026-06-18",
    "est": 2.4398
  },
  "014881": {
    "date": "2026-06-18",
    "est": 2.4914
  },
  "018345": {
    "date": "2026-06-23",
    "est": -1.0873
  },
  "024769": {
    "date": "2026-06-18",
    "est": 2.5605
  },
  "020973": {
    "date": "2026-06-18",
    "est": 2.0967
  },
  "020982": {
    "date": "2026-06-18",
    "est": 2.5147
  },
  "024389": {
    "date": "2026-06-23",
    "est": -2.3107
  },
  "013817": {
    "date": "2026-06-23",
    "est": -5.0432
  },
  "012680": {
    "date": "2026-06-23",
    "est": -4.3269
  },
  "013602": {
    "date": "2026-06-23",
    "est": -4.7884
  },
  "012929": {
    "date": "2026-06-23",
    "est": -4.7927
  },
  "024060": {
    "date": "2026-06-23",
    "est": -4.8084
  },
  "012365": {
    "date": "2026-06-23",
    "est": -4.5816
  },
  "012723": {
    "date": "2026-06-23",
    "est": -4.5547
  },
  "011103": {
    "date": "2026-06-23",
    "est": -4.5919
  },
  "018503": {
    "date": "2026-06-23",
    "est": -4.5967
  },
  "017647": {
    "date": "2026-06-23",
    "est": -4.8227
  },
  "007509": {
    "date": "2026-06-18",
    "est": -1.671
  },
  "011967": {
    "date": "2026-06-23",
    "est": -4.5587
  },
  "012886": {
    "date": "2026-06-23",
    "est": -4.8346
  },
  "007083": {
    "date": "2026-06-18",
    "est": -2.1364
  },
  "011579": {
    "date": "2026-06-23",
    "est": -3.5348
  },
  "014918": {
    "date": "2026-06-23",
    "est": -4.3869
  },
  "017787": {
    "date": "2026-06-23",
    "est": -1.4063
  },
  "019244": {
    "date": "2026-06-23",
    "est": -3.9378
  },
  "013275": {
    "date": "2026-06-23",
    "est": -1.3743
  },
  "016814": {
    "date": "2026-06-23",
    "est": -1.5705
  },
  "012734": {
    "date": "2026-06-23",
    "est": -3.2009
  },
  "008280": {
    "date": "2026-06-23",
    "est": -0.9444
  },
  "013596": {
    "date": "2026-06-18",
    "est": -3.1828
  },
  "015566": {
    "date": "2026-06-23",
    "est": -1.5391
  },
  "008586": {
    "date": "2026-06-23",
    "est": -3.5265
  },
  "011840": {
    "date": "2026-06-23",
    "est": -3.3665
  },
  "023385": {
    "date": "2026-06-23",
    "est": -3.5646
  },
  "014162": {
    "date": "2026-06-23",
    "est": -3.6358
  },
  "005963": {
    "date": "2026-06-23",
    "est": -4.4527
  },
  "024775": {
    "date": "2026-06-23",
    "est": -2.5259
  },
  "024410": {
    "date": "2026-06-23",
    "est": -2.5396
  },
  "023551": {
    "date": "2026-06-23",
    "est": -2.6592
  },
  "023565": {
    "date": "2026-06-23",
    "est": -2.6733
  },
  "024412": {
    "date": "2026-06-23",
    "est": -2.6711
  },
  "024751": {
    "date": "2026-06-23",
    "est": -2.4386
  },
  "023521": {
    "date": "2026-06-23",
    "est": -2.6719
  },
  "024246": {
    "date": "2026-06-23",
    "est": -2.6742
  },
  "008021": {
    "date": "2026-06-23",
    "est": -3.6282
  },
  "023408": {
    "date": "2026-06-23",
    "est": -3.9574
  },
  "024726": {
    "date": "2026-06-23",
    "est": -3.859
  },
  "025493": {
    "date": "2026-06-23",
    "est": -3.8511
  },
  "025506": {
    "date": "2026-06-23",
    "est": -3.8502
  },
  "024663": {
    "date": "2026-06-23",
    "est": -3.8204
  },
  "002164": {
    "date": "2026-06-23",
    "est": -2.9641
  },
  "025857": {
    "date": "2026-06-18",
    "est": 0.2594
  },
  "001665": {
    "date": "2026-06-18",
    "est": 3.5351
  },
  "023639": {
    "date": "2026-06-18",
    "est": 0.9518
  },
  "025793": {
    "date": "2026-06-18",
    "est": 2.3525
  },
  "006113": {
    "date": "2026-06-18",
    "est": 1.1775
  },
  "020137": {
    "date": "2026-06-18",
    "est": 2.1429
  },
  "022150": {
    "date": "2026-06-18",
    "est": 1.8191
  },
  "010500": {
    "date": "2026-06-18",
    "est": 1.8117
  },
  "024358": {
    "date": "2026-06-18",
    "est": 1.4219
  },
  "022287": {
    "date": "2026-06-18",
    "est": 1.7303
  },
  "015916": {
    "date": "2026-06-18",
    "est": 2.5045
  },
  "021760": {
    "date": "2026-06-18",
    "est": 1.3351
  },
  "019917": {
    "date": "2026-06-18",
    "est": 1.0263
  },
  "020232": {
    "date": "2026-06-18",
    "est": 1.7428
  },
  "023482": {
    "date": "2026-06-18",
    "est": 1.4063
  },
  "023598": {
    "date": "2026-06-18",
    "est": 1.4006
  },
  "016971": {
    "date": "2026-06-18",
    "est": 1.3353
  },
  "020111": {
    "date": "2026-06-18",
    "est": 1.0972
  },
  "019671": {
    "date": "2026-06-18",
    "est": 1.3541
  },
  "006229": {
    "date": "2026-06-18",
    "est": 2.8438
  },
  "020398": {
    "date": "2026-06-18",
    "est": 1.9045
  },
  "021031": {
    "date": "2026-06-18",
    "est": 0.9597
  },
  "023930": {
    "date": "2026-06-18",
    "est": 0.9591
  },
  "010655": {
    "date": "2026-06-18",
    "est": 2.42
  },
  "024329": {
    "date": "2026-06-18",
    "est": 0.9642
  },
  "022853": {
    "date": "2026-06-23",
    "est": 1.2084
  },
  "019127": {
    "date": "2026-06-18",
    "est": 1.2045
  },
  "014565": {
    "date": "2026-06-18",
    "est": 2.5141
  },
  "019035": {
    "date": "2026-06-18",
    "est": 1.4175
  },
  "012738": {
    "date": "2026-06-23",
    "est": 0.4999
  },
  "014425": {
    "date": "2026-06-18",
    "est": 1.3528
  },
  "010710": {
    "date": "2026-06-18",
    "est": 0.2098
  },
  "015675": {
    "date": "2026-06-23",
    "est": -2.8033
  },
  "017963": {
    "date": "2026-06-23",
    "est": -0.1266
  },
  "017900": {
    "date": "2026-06-18",
    "est": 2.1778
  },
  "012769": {
    "date": "2026-06-23",
    "est": -1.7225
  },
  "012729": {
    "date": "2026-06-23",
    "est": -1.6643
  },
  "018590": {
    "date": "2026-06-23",
    "est": -2.7307
  },
  "010677": {
    "date": "2026-06-23",
    "est": -2.7778
  },
  "015945": {
    "date": "2026-06-23",
    "est": -1.4461
  },
  "017941": {
    "date": "2026-06-23",
    "est": -2.2779
  },
  "017652": {
    "date": "2026-06-18",
    "est": -0.6535
  },
  "016848": {
    "date": "2026-06-23",
    "est": -2.765
  },
  "018185": {
    "date": "2026-06-23",
    "est": -2.3354
  },
  "010364": {
    "date": "2026-06-18",
    "est": 0.3203
  },
  "008960": {
    "date": "2026-06-23",
    "est": -2.4273
  },
  "012842": {
    "date": "2026-06-18",
    "est": -1.1151
  },
  "018940": {
    "date": "2026-06-23",
    "est": -1.8792
  },
  "013035": {
    "date": "2026-06-18",
    "est": -1.1114
  },
  "015046": {
    "date": "2026-06-18",
    "est": -0.0633
  },
  "015599": {
    "date": "2026-06-18",
    "est": -0.8325
  },
  "005693": {
    "date": "2026-06-18",
    "est": -1.1705
  },
  "018028": {
    "date": "2026-06-18",
    "est": 0.2682
  },
  "013613": {
    "date": "2026-06-23",
    "est": -1.7329
  },
  "018075": {
    "date": "2026-06-23",
    "est": -2.7757
  },
  "022243": {
    "date": "2026-06-23",
    "est": -1.9396
  },
  "020107": {
    "date": "2026-06-23",
    "est": -1.8862
  },
  "013566": {
    "date": "2026-06-23",
    "est": -3.0526
  },
  "023145": {
    "date": "2026-06-23",
    "est": -0.6617
  },
  "021620": {
    "date": "2026-06-23",
    "est": -0.7521
  },
  "021823": {
    "date": "2026-06-23",
    "est": -1.2364
  },
  "020105": {
    "date": "2026-06-23",
    "est": -2.1492
  },
  "023833": {
    "date": "2026-06-23",
    "est": -0.7926
  },
  "017856": {
    "date": "2026-06-23",
    "est": -2.1501
  },
  "020406": {
    "date": "2026-06-23",
    "est": -0.6846
  },
  "019828": {
    "date": "2026-06-23",
    "est": -1.2358
  },
  "019578": {
    "date": "2026-06-18",
    "est": -0.55
  },
  "163208": {
    "date": "2026-06-18",
    "est": -0.539
  },
  "011036": {
    "date": "2026-06-23",
    "est": -5.7228
  },
  "014332": {
    "date": "2026-06-23",
    "est": -6.594
  },
  "019875": {
    "date": "2026-06-23",
    "est": -7.1093
  },
  "011035": {
    "date": "2026-06-18",
    "est": 1.8431
  },
  "019088": {
    "date": "2026-06-23",
    "est": -7.1899
  },
  "013943": {
    "date": "2026-06-23",
    "est": -6.4808
  },
  "004937": {
    "date": "2026-06-23",
    "est": -7.3153
  },
  "014111": {
    "date": "2026-06-23",
    "est": -6.8575
  },
  "019874": {
    "date": "2026-06-18",
    "est": -0.7872
  },
  "017057": {
    "date": "2026-06-23",
    "est": -0.5189
  },
  "016186": {
    "date": "2026-06-23",
    "est": -0.8861
  },
  "021753": {
    "date": "2026-06-23",
    "est": -0.1875
  },
  "017175": {
    "date": "2026-06-23",
    "est": -0.2639
  },
  "018173": {
    "date": "2026-06-18",
    "est": -2.2928
  },
  "018735": {
    "date": "2026-06-23",
    "est": -0.2249
  },
  "017482": {
    "date": "2026-06-23",
    "est": -0.1865
  },
  "019059": {
    "date": "2026-06-23",
    "est": -0.2263
  },
  "020096": {
    "date": "2026-06-23",
    "est": -0.2221
  },
  "018035": {
    "date": "2026-06-23",
    "est": -0.2742
  },
  "006533": {
    "date": "2026-06-18",
    "est": 2.5878
  },
  "008327": {
    "date": "2026-06-23",
    "est": -3.4864
  },
  "020900": {
    "date": "2026-06-23",
    "est": -3.1025
  },
  "020692": {
    "date": "2026-06-23",
    "est": -3.1472
  },
  "021934": {
    "date": "2026-06-23",
    "est": -3.6987
  },
  "022328": {
    "date": "2026-06-23",
    "est": -0.4462
  },
  "012538": {
    "date": "2026-06-18",
    "est": -2.9947
  },
  "019237": {
    "date": "2026-06-23",
    "est": 0.0002
  },
  "017668": {
    "date": "2026-06-23",
    "est": -3.0674
  },
  "014943": {
    "date": "2026-06-18",
    "est": -2.5476
  },
  "007818": {
    "date": "2026-06-23",
    "est": -3.1025
  },
  "017836": {
    "date": "2026-06-23",
    "est": -2.8024
  },
  "290014": {
    "date": "2026-06-23",
    "est": -4.3367
  },
  "025778": {
    "date": "2026-06-23",
    "est": -5.9452
  },
  "012710": {
    "date": "2026-06-23",
    "est": -5.3905
  },
  "290008": {
    "date": "2026-06-23",
    "est": -5.6332
  },
  "008087": {
    "date": "2026-06-23",
    "est": -0.0804
  },
  "019235": {
    "date": "2026-06-23",
    "est": -5.4186
  },
  "017037": {
    "date": "2026-06-23",
    "est": -2.019
  },
  "012355": {
    "date": "2026-06-23",
    "est": -4.0292
  },
  "014766": {
    "date": "2026-06-23",
    "est": -4.7129
  },
  "011261": {
    "date": "2026-06-23",
    "est": -2.9674
  },
  "017840": {
    "date": "2026-06-23",
    "est": -3.6172
  },
  "020274": {
    "date": "2026-06-18",
    "est": -0.027
  },
  "025833": {
    "date": "2026-06-18",
    "est": 0.9912
  },
  "008701": {
    "date": "2026-06-18",
    "est": -0.53
  },
  "014662": {
    "date": "2026-06-23",
    "est": -1.99
  },
  "008987": {
    "date": "2026-06-23",
    "est": -1.9
  },
  "009505": {
    "date": "2026-06-23",
    "est": -1.87
  },
  "009034": {
    "date": "2026-06-23",
    "est": -1.87
  },
  "016582": {
    "date": "2026-06-23",
    "est": -2.0
  },
  "009478": {
    "date": "2026-06-23",
    "est": -1.87
  },
  "018392": {
    "date": "2026-06-23",
    "est": -1.99
  },
  "002963": {
    "date": "2026-06-23",
    "est": -2.03
  },
  "008702": {
    "date": "2026-06-23",
    "est": -1.88
  },
  "004253": {
    "date": "2026-06-23",
    "est": -1.88
  },
  "008143": {
    "date": "2026-06-23",
    "est": -1.9
  },
  "000217": {
    "date": "2026-06-23",
    "est": -1.9
  },
  "021740": {
    "date": "2026-06-23",
    "est": -1.99
  },
  "002611": {
    "date": "2026-06-23",
    "est": -2.01
  },
  "007844": {
    "date": "2026-06-18",
    "est": -0.94
  },
  "162411": {
    "date": "2026-06-18",
    "est": -0.94
  },
  "004243": {
    "date": "2026-06-18",
    "est": -0.93
  },
  "014982": {
    "date": "2026-06-18",
    "est": -0.53
  },
  "018853": {
    "date": "2026-06-18",
    "est": -0.84
  },
  "160723": {
    "date": "2026-06-18",
    "est": -0.1736
  },
  "014353": {
    "date": "2026-06-23",
    "est": -3.5692
  },
  "005359": {
    "date": "2026-06-23",
    "est": -3.9306
  },
  "016389": {
    "date": "2026-06-23",
    "est": -3.4238
  },
  "020433": {
    "date": "2026-06-23",
    "est": -3.7669
  },
  "017916": {
    "date": "2026-06-23",
    "est": -1.9241
  },
  "019903": {
    "date": "2026-06-23",
    "est": -3.6024
  },
  "025331": {
    "date": "2026-06-23",
    "est": -2.1028
  },
  "001532": {
    "date": "2026-06-23",
    "est": -2.7624
  },
  "001482": {
    "date": "2026-06-23",
    "est": -3.3909
  },
  "005669": {
    "date": "2026-06-23",
    "est": -2.0254
  },
  "007732": {
    "date": "2026-06-23",
    "est": -2.8467
  },
  "014581": {
    "date": "2026-06-23",
    "est": -3.6277
  },
  "018817": {
    "date": "2026-06-23",
    "est": -2.5446
  },
  "010842": {
    "date": "2026-06-23",
    "est": -1.4628
  },
  "022644": {
    "date": "2026-06-23",
    "est": -3.4984
  },
  "016008": {
    "date": "2026-06-23",
    "est": 0.0001
  },
  "015895": {
    "date": "2026-06-23",
    "est": -0.0195
  },
  "015877": {
    "date": "2026-06-23",
    "est": -0.006
  },
  "020984": {
    "date": "2026-06-23",
    "est": -3.5028
  },
  "018897": {
    "date": "2026-06-23",
    "est": -3.5975
  },
  "012320": {
    "date": "2026-06-18",
    "est": 2.614
  },
  "018301": {
    "date": "2026-06-23",
    "est": -3.5975
  },
  "001618": {
    "date": "2026-06-23",
    "est": -0.0853
  },
  "014544": {
    "date": "2026-06-23",
    "est": -2.795
  },
  "014130": {
    "date": "2026-06-23",
    "est": -3.2942
  },
  "019170": {
    "date": "2026-06-23",
    "est": -0.1615
  },
  "012322": {
    "date": "2026-06-23",
    "est": -3.3531
  },
  "019331": {
    "date": "2026-06-23",
    "est": -0.0028
  },
  "025791": {
    "date": "2026-06-23",
    "est": -2.96
  },
  "017854": {
    "date": "2026-06-23",
    "est": -3.3531
  },
  "019869": {
    "date": "2026-06-23",
    "est": -3.01
  },
  "021398": {
    "date": "2026-06-23",
    "est": -0.0016
  },
  "020336": {
    "date": "2026-06-23",
    "est": -2.62
  },
  "018135": {
    "date": "2026-06-23",
    "est": -0.0134
  },
  "021091": {
    "date": "2026-06-23",
    "est": -2.95
  },
  "021717": {
    "date": "2026-06-23",
    "est": -2.96
  },
  "026383": {
    "date": "2026-06-23",
    "est": -1.6416
  },
  "006271": {
    "date": "2026-06-23",
    "est": -0.5711
  },
  "519173": {
    "date": "2026-06-23",
    "est": -0.3732
  },
  "013340": {
    "date": "2026-06-23",
    "est": -0.4783
  },
  "016523": {
    "date": "2026-06-23",
    "est": -3.732
  },
  "018123": {
    "date": "2026-06-23",
    "est": -2.2173
  },
  "021511": {
    "date": "2026-06-23",
    "est": -1.0688
  },
  "006719": {
    "date": "2026-06-23",
    "est": -2.0092
  },
  "019427": {
    "date": "2026-06-23",
    "est": -1.8083
  },
  "009708": {
    "date": "2026-06-23",
    "est": -1.212
  },
  "020470": {
    "date": "2026-06-23",
    "est": -1.5793
  },
  "014497": {
    "date": "2026-06-23",
    "est": -1.8871
  },
  "023045": {
    "date": "2026-06-23",
    "est": -1.1602
  },
  "014419": {
    "date": "2026-06-23",
    "est": -2.5774
  },
  "003235": {
    "date": "2026-06-18",
    "est": 1.2225
  },
  "026994": {
    "date": "2026-06-23",
    "est": -2.35
  },
  "state": {
    "date": "2026-06-03",
    "est": 2.7737
  },
  "011833": {
    "date": "2026-06-23",
    "est": -3.1654
  },
  "027034": {
    "date": "2026-06-23",
    "est": -2.98
  },
  "009239": {
    "date": "2026-06-23",
    "est": -3.3173
  },
  "024561": {
    "date": "2026-06-23",
    "est": -0.0022
  },
  "026613": {
    "date": "2026-06-23",
    "est": -2.37
  },
  "002052": {
    "date": "2026-06-23",
    "est": -2.8861
  },
  "023286": {
    "date": "2026-06-23",
    "est": -2.0809
  },
  "025653": {
    "date": "2026-06-23",
    "est": -0.0202
  },
  "015773": {
    "date": "2026-06-23",
    "est": -1.959
  },
  "022891": {
    "date": "2026-06-23",
    "est": -2.8702
  },
  "001606": {
    "date": "2026-06-23",
    "est": -1.3383
  },
  "013446": {
    "date": "2026-06-23",
    "est": -1.4
  },
  "002163": {
    "date": "2026-06-23",
    "est": -0.7277
  },
  "519172": {
    "date": "2026-06-23",
    "est": -0.3732
  },
  "012651": {
    "date": "2026-06-23",
    "est": -2.5188
  },
  "026623": {
    "date": "2026-06-23",
    "est": -2.6723
  },
  "026213": {
    "date": "2026-06-23",
    "est": -0.3093
  },
  "020227": {
    "date": "2026-06-22",
    "est": 2.36
  },
  "016501": {
    "date": "2026-06-22",
    "est": 2.0606
  },
  "012697": {
    "date": "2026-06-22",
    "est": 3.9517
  },
  "013312": {
    "date": "2026-06-23",
    "est": 0.0984
  },
  "021627": {
    "date": "2026-06-23",
    "est": -0.6593
  },
  "014549": {
    "date": "2026-06-22",
    "est": 2.7762
  },
  "002051": {
    "date": "2026-06-23",
    "est": -1.1136
  },
  "008981": {
    "date": "2026-06-23",
    "est": -3.1342
  },
  "017076": {
    "date": "2026-06-23",
    "est": -1.4614
  },
  "022868": {
    "date": "2026-06-23",
    "est": -4.4526
  },
  "014953": {
    "date": "2026-06-23",
    "est": -0.8766
  },
  "016234": {
    "date": "2026-06-23",
    "est": -2.7538
  },
  "020436": {
    "date": "2026-06-23",
    "est": -1.7535
  },
  "020671": {
    "date": "2026-06-23",
    "est": -1.5886
  },
  "019764": {
    "date": "2026-06-23",
    "est": -2.9361
  },
  "020451": {
    "date": "2026-06-23",
    "est": -1.7411
  },
  "019925": {
    "date": "2026-06-22",
    "est": 3.002
  },
  "007301": {
    "date": "2026-06-23",
    "est": -1.2
  },
  "022335": {
    "date": "2026-06-23",
    "est": -1.142
  },
  "025333": {
    "date": "2026-06-23",
    "est": -0.1835
  },
  "014737": {
    "date": "2026-06-23",
    "est": -1.3968
  },
  "023452": {
    "date": "2026-06-23",
    "est": -4.2466
  },
  "023095": {
    "date": "2026-06-23",
    "est": -1.8186
  },
  "020662": {
    "date": "2026-06-23",
    "est": -2.8852
  },
  "001470": {
    "date": "2026-06-22",
    "est": 0.0399
  },
  "018998": {
    "date": "2026-06-23",
    "est": -2.3829
  },
  "004569": {
    "date": "2026-06-23",
    "est": -2.8971
  },
  "024169": {
    "date": "2026-06-23",
    "est": -0.3447
  },
  "002418": {
    "date": "2026-06-23",
    "est": -3.3924
  },
  "008989": {
    "date": "2026-06-23",
    "est": -2.8989
  },
  "001608": {
    "date": "2026-06-23",
    "est": -4.1848
  },
  "014784": {
    "date": "2026-06-23",
    "est": -2.4105
  },
  "519158": {
    "date": "2026-06-23",
    "est": -2.9699
  },
  "021989": {
    "date": "2026-06-23",
    "est": -3.5413
  },
  "001040": {
    "date": "2026-06-23",
    "est": -3.1053
  },
  "026539": {
    "date": "2026-06-23",
    "est": -2.34
  },
  "025759": {
    "date": "2026-06-23",
    "est": -3.2479
  },
  "016579": {
    "date": "2026-06-22",
    "est": 2.3263
  },
  "018495": {
    "date": "2026-06-22",
    "est": 6.4262
  },
  "024477": {
    "date": "2026-06-23",
    "est": -3.6486
  },
  "020661": {
    "date": "2026-06-22",
    "est": 0.4947
  },
  "011814": {
    "date": "2026-06-22",
    "est": 1.7587
  },
  "020705": {
    "date": "2026-06-23",
    "est": -2.44
  },
  "008382": {
    "date": "2026-06-22",
    "est": 5.6783
  },
  "501205": {
    "date": "2026-06-22",
    "est": 3.6653
  },
  "460007": {
    "date": "2026-06-22",
    "est": 2.3275
  },
  "026155": {
    "date": "2026-06-22",
    "est": 1.6885
  },
  "021957": {
    "date": "2026-06-22",
    "est": 2.4547
  },
  "019830": {
    "date": "2026-06-23",
    "est": -3.8867
  },
  "018211": {
    "date": "2026-06-22",
    "est": 2.4079
  },
  "006372": {
    "date": "2026-06-22",
    "est": 3.4748
  },
  "015665": {
    "date": "2026-06-22",
    "est": 3.3388
  },
  "017761": {
    "date": "2026-06-22",
    "est": 2.7888
  },
  "011112": {
    "date": "2026-06-22",
    "est": 2.7169
  },
  "026211": {
    "date": "2026-06-23",
    "est": -2.3075
  },
  "501201": {
    "date": "2026-06-22",
    "est": 2.6766
  },
  "025660": {
    "date": "2026-06-23",
    "est": -3.1797
  },
  "021383": {
    "date": "2026-06-22",
    "est": 4.0412
  },
  "019072": {
    "date": "2026-06-23",
    "est": -0.0029
  },
  "025783": {
    "date": "2026-06-22",
    "est": 1.5391
  },
  "018288": {
    "date": "2026-06-22",
    "est": 0.3895
  },
  "019024": {
    "date": "2026-06-23",
    "est": -2.7232
  },
  "018828": {
    "date": "2026-06-22",
    "est": 0.9962
  },
  "001956": {
    "date": "2026-06-23",
    "est": -2.3114
  },
  "015772": {
    "date": "2026-06-22",
    "est": 1.1912
  },
  "021313": {
    "date": "2026-06-22",
    "est": 0.2091
  },
  "012497": {
    "date": "2026-06-22",
    "est": -1.6813
  },
  "015389": {
    "date": "2026-06-23",
    "est": -1.9845
  },
  "008555": {
    "date": "2026-06-22",
    "est": 7.2468
  },
  "012546": {
    "date": "2026-06-22",
    "est": 1.3381
  },
  "021542": {
    "date": "2026-06-23",
    "est": -3.6843
  },
  "213003": {
    "date": "2026-06-22",
    "est": -0.8779
  },
  "026245": {
    "date": "2026-06-22",
    "est": 2.6642
  },
  "519005": {
    "date": "2026-06-22",
    "est": 1.164
  },
  "011400": {
    "date": "2026-06-22",
    "est": 3.7286
  },
  "009243": {
    "date": "2026-06-22",
    "est": 2.2787
  },
  "024434": {
    "date": "2026-06-22",
    "est": 4.4499
  },
  "016508": {
    "date": "2026-06-22",
    "est": 1.501
  },
  "002272": {
    "date": "2026-06-22",
    "est": -0.8462
  },
  "013883": {
    "date": "2026-06-22",
    "est": 6.0777
  },
  "025348": {
    "date": "2026-06-22",
    "est": 3.8395
  },
  "005875": {
    "date": "2026-06-22",
    "est": 3.1574
  },
  "006080": {
    "date": "2026-06-22",
    "est": 1.5207
  },
  "011412": {
    "date": "2026-06-23",
    "est": -3.3899
  },
  "002771": {
    "date": "2026-06-23",
    "est": -3.8801
  },
  "021523": {
    "date": "2026-06-23",
    "est": -2.418
  },
  "015097": {
    "date": "2026-06-22",
    "est": -0.0575
  },
  "024460": {
    "date": "2026-06-23",
    "est": -3.9543
  },
  "026137": {
    "date": "2026-06-22",
    "est": -1.1743
  },
  "020018": {
    "date": "2026-06-23",
    "est": -1.2671
  },
  "025191": {
    "date": "2026-06-22",
    "est": 3.5613
  },
  "016173": {
    "date": "2026-06-22",
    "est": 4.5635
  },
  "006616": {
    "date": "2026-06-22",
    "est": 3.1486
  },
  "008984": {
    "date": "2026-06-23",
    "est": -0.6198
  },
  "025881": {
    "date": "2026-06-23",
    "est": -2.7718
  },
  "013145": {
    "date": "2026-06-22",
    "est": 2.6482
  },
  "015576": {
    "date": "2026-06-22",
    "est": 3.7723
  },
  "180031": {
    "date": "2026-06-23",
    "est": -2.8822
  },
  "024692": {
    "date": "2026-06-22",
    "est": 0.2353
  },
  "017612": {
    "date": "2026-06-23",
    "est": -3.8073
  },
  "540010": {
    "date": "2026-06-22",
    "est": 0.4356
  },
  "010416": {
    "date": "2026-06-23",
    "est": -4.1517
  },
  "018933": {
    "date": "2026-06-22",
    "est": -0.1494
  },
  "026476": {
    "date": "2026-06-23",
    "est": -2.34
  },
  "006523": {
    "date": "2026-06-22",
    "est": 3.0329
  },
  "162201": {
    "date": "2026-06-22",
    "est": 3.509
  },
  "024593": {
    "date": "2026-06-23",
    "est": -3.9096
  },
  "005959": {
    "date": "2026-06-22",
    "est": 2.4257
  },
  "001416": {
    "date": "2026-06-22",
    "est": 4.0409
  },
  "002768": {
    "date": "2026-06-22",
    "est": 0.6552
  },
  "017724": {
    "date": "2026-06-22",
    "est": -0.3987
  },
  "012617": {
    "date": "2026-06-23",
    "est": -3.6226
  },
  "020441": {
    "date": "2026-06-22",
    "est": 0.7421
  },
  "022124": {
    "date": "2026-06-22",
    "est": 6.3658
  },
  "022177": {
    "date": "2026-06-23",
    "est": -3.4629
  },
  "025957": {
    "date": "2026-06-23",
    "est": -1.8473
  },
  "501096": {
    "date": "2026-06-23",
    "est": -0.9576
  },
  "024481": {
    "date": "2026-06-23",
    "est": -2.881
  },
  "022718": {
    "date": "2026-06-23",
    "est": -1.4736
  },
  "023421": {
    "date": "2026-06-23",
    "est": -1.3422
  },
  "011829": {
    "date": "2026-06-23",
    "est": -3.3073
  },
  "009883": {
    "date": "2026-06-23",
    "est": -3.1605
  },
  "002839": {
    "date": "2026-06-23",
    "est": -3.7277
  },
  "005934": {
    "date": "2026-06-23",
    "est": -5.8949
  },
  "002365": {
    "date": "2026-06-23",
    "est": -0.2327
  },
  "013073": {
    "date": "2026-06-23",
    "est": 3.5109
  },
  "010091": {
    "date": "2026-06-23",
    "est": 2.7266
  },
  "007553": {
    "date": "2026-06-23",
    "est": 2.3068
  },
  "010031": {
    "date": "2026-06-23",
    "est": 2.2575
  },
  "019029": {
    "date": "2026-06-23",
    "est": 1.9523
  },
  "010159": {
    "date": "2026-06-23",
    "est": 2.2013
  },
  "015562": {
    "date": "2026-06-23",
    "est": 1.3957
  },
  "010685": {
    "date": "2026-06-23",
    "est": 0.9918
  },
  "002938": {
    "date": "2026-06-23",
    "est": 1.1213
  },
  "004041": {
    "date": "2026-06-23",
    "est": 1.7502
  },
  "003231": {
    "date": "2026-06-23",
    "est": 2.2936
  },
  "012782": {
    "date": "2026-06-23",
    "est": 1.51
  },
  "007862": {
    "date": "2026-06-23",
    "est": 2.9475
  },
  "021098": {
    "date": "2026-06-23",
    "est": 1.5
  },
  "016387": {
    "date": "2026-06-23",
    "est": -2.1705
  },
  "167002": {
    "date": "2026-06-23",
    "est": -3.9982
  },
  "026681": {
    "date": "2026-06-23",
    "est": -3.6945
  },
  "019411": {
    "date": "2026-06-23",
    "est": -2.9548
  },
  "017133": {
    "date": "2026-06-23",
    "est": -4.5466
  },
  "017042": {
    "date": "2026-06-23",
    "est": -4.3436
  },
  "010913": {
    "date": "2026-06-23",
    "est": 0.0309
  },
  "026633": {
    "date": "2026-06-23",
    "est": -0.0528
  },
  "014989": {
    "date": "2026-06-23",
    "est": 0.1089
  },
  "005629": {
    "date": "2026-06-23",
    "est": -0.9852
  },
  "015585": {
    "date": "2026-06-23",
    "est": 0.1371
  },
  "016262": {
    "date": "2026-06-23",
    "est": -0.291
  },
  "017747": {
    "date": "2026-06-23",
    "est": -0.1392
  },
  "013841": {
    "date": "2026-06-23",
    "est": 0.0637
  },
  "014300": {
    "date": "2026-06-23",
    "est": -0.4384
  },
  "025687": {
    "date": "2026-06-23",
    "est": -0.1569
  },
  "025969": {
    "date": "2026-06-23",
    "est": 0.2721
  },
  "011378": {
    "date": "2026-06-23",
    "est": -0.9915
  },
  "007343": {
    "date": "2026-06-23",
    "est": -1.0625
  },
  "016721": {
    "date": "2026-06-23",
    "est": -1.1497
  },
  "021594": {
    "date": "2026-06-23",
    "est": -1.1853
  },
  "027329": {
    "date": "2026-06-23",
    "est": 0.29
  },
  "021180": {
    "date": "2026-06-23",
    "est": -0.1078
  },
  "007639": {
    "date": "2026-06-23",
    "est": 0.339
  },
  "162214": {
    "date": "2026-06-23",
    "est": -0.0079
  },
  "026834": {
    "date": "2026-06-23",
    "est": -3.376
  },
  "026385": {
    "date": "2026-06-23",
    "est": -3.5601
  },
  "013044": {
    "date": "2026-06-23",
    "est": -2.3673
  },
  "019213": {
    "date": "2026-06-23",
    "est": -2.7178
  },
  "026563": {
    "date": "2026-06-23",
    "est": -0.2577
  },
  "001537": {
    "date": "2026-06-23",
    "est": -0.968
  },
  "021095": {
    "date": "2026-06-23",
    "est": 0.2762
  },
  "024203": {
    "date": "2026-06-23",
    "est": -1.3886
  },
  "003153": {
    "date": "2026-06-23",
    "est": -0.0901
  },
  "021943": {
    "date": "2026-06-23",
    "est": -0.9173
  },
  "017628": {
    "date": "2026-06-23",
    "est": -3.4604
  },
  "001252": {
    "date": "2026-06-23",
    "est": -4.5508
  },
  "024224": {
    "date": "2026-06-23",
    "est": -3.5324
  },
  "001294": {
    "date": "2026-06-23",
    "est": -4.0746
  },
  "018249": {
    "date": "2026-06-23",
    "est": -2.6539
  },
  "014422": {
    "date": "2026-06-23",
    "est": -3.1116
  },
  "011592": {
    "date": "2026-06-23",
    "est": -2.6567
  },
  "019395": {
    "date": "2026-06-23",
    "est": -2.6819
  },
  "006133": {
    "date": "2026-06-23",
    "est": -2.8186
  },
  "020987": {
    "date": "2026-06-23",
    "est": -3.2013
  },
  "018203": {
    "date": "2026-06-23",
    "est": -2.2685
  },
  "024842": {
    "date": "2026-06-23",
    "est": -1.5462
  },
  "016924": {
    "date": "2026-06-23",
    "est": -1.7101
  },
  "017649": {
    "date": "2026-06-23",
    "est": -2.2732
  },
  "016847": {
    "date": "2026-06-23",
    "est": -2.7759
  },
  "016561": {
    "date": "2026-06-23",
    "est": -3.7637
  },
  "013618": {
    "date": "2026-06-23",
    "est": -2.1469
  },
  "011185": {
    "date": "2026-06-23",
    "est": -1.2757
  },
  "011113": {
    "date": "2026-06-23",
    "est": -1.8255
  },
  "010741": {
    "date": "2026-06-23",
    "est": -2.6446
  },
  "002017": {
    "date": "2026-06-23",
    "est": -2.2422
  },
  "014962": {
    "date": "2026-06-23",
    "est": -1.6825
  },
  "005542": {
    "date": "2026-06-23",
    "est": -2.005
  },
  "026126": {
    "date": "2026-06-23",
    "est": -1.4853
  },
  "004522": {
    "date": "2026-06-23",
    "est": -1.9149
  },
  "001864": {
    "date": "2026-06-23",
    "est": -0.9127
  },
  "001271": {
    "date": "2026-06-23",
    "est": -1.1441
  },
  "014700": {
    "date": "2026-06-23",
    "est": -1.2249
  },
  "017461": {
    "date": "2026-06-23",
    "est": -1.5866
  },
  "014243": {
    "date": "2026-06-23",
    "est": -1.0509
  },
  "002053": {
    "date": "2026-06-23",
    "est": -1.2444
  },
  "000794": {
    "date": "2026-06-23",
    "est": -1.3776
  },
  "001830": {
    "date": "2026-06-23",
    "est": -1.587
  },
  "005297": {
    "date": "2026-06-23",
    "est": -0.7252
  },
  "003835": {
    "date": "2026-06-23",
    "est": -1.1268
  },
  "016635": {
    "date": "2026-06-23",
    "est": -1.8019
  },
  "014939": {
    "date": "2026-06-23",
    "est": 1.1922
  },
  "024648": {
    "date": "2026-06-23",
    "est": -1.4527
  },
  "004233": {
    "date": "2026-06-23",
    "est": -1.5996
  },
  "008998": {
    "date": "2026-06-23",
    "est": 1.2111
  },
  "024262": {
    "date": "2026-06-23",
    "est": -1.5956
  },
  "013349": {
    "date": "2026-06-23",
    "est": 1.2229
  },
  "011003": {
    "date": "2026-06-23",
    "est": -0.0487
  },
  "025637": {
    "date": "2026-06-23",
    "est": 0.5639
  },
  "026639": {
    "date": "2026-06-23",
    "est": 0.2558
  },
  "019414": {
    "date": "2026-06-23",
    "est": 0.9747
  },
  "026825": {
    "date": "2026-06-23",
    "est": 0.0883
  },
  "001056": {
    "date": "2026-06-23",
    "est": 0.6455
  },
  "017213": {
    "date": "2026-06-23",
    "est": 0.8455
  },
  "018089": {
    "date": "2026-06-23",
    "est": 1.3412
  },
  "015254": {
    "date": "2026-06-23",
    "est": -1.7278
  },
  "013278": {
    "date": "2026-06-23",
    "est": -1.673
  },
  "003054": {
    "date": "2026-06-23",
    "est": -1.0485
  },
  "004846": {
    "date": "2026-06-23",
    "est": -0.7042
  },
  "017825": {
    "date": "2026-06-23",
    "est": -3.5019
  },
  "015005": {
    "date": "2026-06-23",
    "est": -2.9083
  },
  "013050": {
    "date": "2026-06-23",
    "est": -3.2194
  },
  "006122": {
    "date": "2026-06-23",
    "est": -3.8446
  },
  "025395": {
    "date": "2026-06-23",
    "est": -3.6115
  },
  "024257": {
    "date": "2026-06-23",
    "est": -0.8266
  },
  "000929": {
    "date": "2026-06-23",
    "est": -1.77
  },
  "005210": {
    "date": "2026-06-23",
    "est": -1.6682
  },
  "013104": {
    "date": "2026-06-23",
    "est": -3.4761
  },
  "002084": {
    "date": "2026-06-23",
    "est": -5.5472
  },
  "020682": {
    "date": "2026-06-23",
    "est": -3.7703
  },
  "018419": {
    "date": "2026-06-23",
    "est": -3.644
  },
  "012127": {
    "date": "2026-06-23",
    "est": -4.8133
  },
  "013188": {
    "date": "2026-06-23",
    "est": -3.343
  },
  "011480": {
    "date": "2026-06-23",
    "est": -3.3871
  },
  "026716": {
    "date": "2026-06-23",
    "est": -1.14
  },
  "021856": {
    "date": "2026-06-23",
    "est": -0.0118
  },
  "015928": {
    "date": "2026-06-23",
    "est": -2.9732
  },
  "016981": {
    "date": "2026-06-23",
    "est": -4.4003
  },
  "026069": {
    "date": "2026-06-23",
    "est": -4.1136
  },
  "015994": {
    "date": "2026-06-23",
    "est": -4.3003
  },
  "019532": {
    "date": "2026-06-23",
    "est": -4.5966
  },
  "014605": {
    "date": "2026-06-23",
    "est": 0.0058
  },
  "013511": {
    "date": "2026-06-23",
    "est": -3.0188
  },
  "014423": {
    "date": "2026-06-23",
    "est": -4.1746
  },
  "001644": {
    "date": "2026-06-23",
    "est": -3.5337
  },
  "016335": {
    "date": "2026-06-23",
    "est": -3.402
  },
  "024896": {
    "date": "2026-06-23",
    "est": -7.1402
  },
  "021297": {
    "date": "2026-06-23",
    "est": -7.78
  },
  "018656": {
    "date": "2026-06-23",
    "est": -2.8633
  },
  "021637": {
    "date": "2026-06-23",
    "est": -7.3825
  },
  "016341": {
    "date": "2026-06-23",
    "est": -4.7992
  },
  "630011": {
    "date": "2026-06-23",
    "est": -6.345
  },
  "002288": {
    "date": "2026-06-23",
    "est": -6.3682
  },
  "026478": {
    "date": "2026-06-23",
    "est": 0.0
  },
  "017141": {
    "date": "2026-06-23",
    "est": -7.74
  },
  "008179": {
    "date": "2026-06-23",
    "est": -8.2955
  },
  "024831": {
    "date": "2026-06-23",
    "est": -5.5809
  },
  "017599": {
    "date": "2026-06-23",
    "est": -6.8322
  },
  "007776": {
    "date": "2026-06-23",
    "est": -7.6403
  },
  "003625": {
    "date": "2026-06-23",
    "est": -7.7502
  },
  "005660": {
    "date": "2026-06-23",
    "est": -7.344
  },
  "019305": {
    "date": "2026-06-23",
    "est": 0.28
  },
  "012860": {
    "date": "2026-06-23",
    "est": 0.26
  },
  "012815": {
    "date": "2026-06-23",
    "est": -2.8485
  },
  "024641": {
    "date": "2026-06-23",
    "est": -2.5996
  },
  "008401": {
    "date": "2026-06-23",
    "est": 0.27
  },
  "017885": {
    "date": "2026-06-23",
    "est": -2.0033
  },
  "018195": {
    "date": "2026-06-23",
    "est": -2.7909
  },
  "000593": {
    "date": "2026-06-23",
    "est": -3.0458
  },
  "002423": {
    "date": "2026-06-23",
    "est": 0.28
  },
  "009975": {
    "date": "2026-06-23",
    "est": 0.28
  },
  "014521": {
    "date": "2026-06-23",
    "est": -2.1154
  },
  "020487": {
    "date": "2026-06-23",
    "est": -1.813
  },
  "016450": {
    "date": "2026-06-23",
    "est": -1.1868
  },
  "015770": {
    "date": "2026-06-23",
    "est": -1.0138
  },
  "001402": {
    "date": "2026-06-23",
    "est": -1.8431
  },
  "015455": {
    "date": "2026-06-23",
    "est": -2.7152
  },
  "022167": {
    "date": "2026-06-23",
    "est": -5.6877
  },
  "011426": {
    "date": "2026-06-23",
    "est": -0.6912
  },
  "022447": {
    "date": "2026-06-23",
    "est": -5.5849
  },
  "519191": {
    "date": "2026-06-23",
    "est": -1.0801
  },
  "023840": {
    "date": "2026-06-23",
    "est": -2.3433
  },
  "026489": {
    "date": "2026-06-23",
    "est": -1.86
  },
  "010235": {
    "date": "2026-06-23",
    "est": -0.7621
  },
  "016347": {
    "date": "2026-06-23",
    "est": -0.7367
  },
  "024239": {
    "date": "2026-06-23",
    "est": 0.12
  },
  "017173": {
    "date": "2026-06-23",
    "est": 0.0
  },
  "019593": {
    "date": "2026-06-23",
    "est": -0.0079
  },
  "100055": {
    "date": "2026-06-23",
    "est": -2.005
  },
  "017731": {
    "date": "2026-06-23",
    "est": -1.8956
  },
  "016823": {
    "date": "2026-06-23",
    "est": 0.16
  },
  "017654": {
    "date": "2026-06-23",
    "est": -0.4306
  },
  "021277": {
    "date": "2026-06-23",
    "est": -8.3916
  },
  "019156": {
    "date": "2026-06-23",
    "est": -5.7775
  },
  "018036": {
    "date": "2026-06-23",
    "est": 0.21
  },
  "002891": {
    "date": "2026-06-23",
    "est": 0.23
  },
  "019034": {
    "date": "2026-06-23",
    "est": -2.2335
  },
  "011126": {
    "date": "2026-06-23",
    "est": -4.2047
  },
  "014642": {
    "date": "2026-06-23",
    "est": -4.1414
  },
  "019018": {
    "date": "2026-06-23",
    "est": -2.0918
  },
  "005551": {
    "date": "2026-06-23",
    "est": -1.7754
  },
  "018994": {
    "date": "2026-06-23",
    "est": -4.1701
  }
}